BenchMatcha/__init__.py
BenchMatcha/complexity.py
BenchMatcha/config.py
BenchMatcha/errors.py
BenchMatcha/handlers.py
BenchMatcha/plotting.py
BenchMatcha/py.typed
BenchMatcha/runner.py
BenchMatcha/sifter.py
BenchMatcha/structure.py
BenchMatcha/utils.py
benchmatcha-0.0.1.dist-info/licenses/LICENSE
benchmatcha-0.0.1.dist-info/METADATA
benchmatcha-0.0.1.dist-info/WHEEL
benchmatcha-0.0.1.dist-info/entry_points.txt
benchmatcha-0.0.1.dist-info/top_level.txt
benchmatcha-0.0.1.dist-info/RECORD
