Metadata-Version: 2.4
Name: BenchMatcha
Version: 0.0.1
Summary: Google Benchmark Suite Runner and Regression Analyzer.
Author-email: Jason C Del Rio <spillthetea917@gmail.com>
Maintainer-email: Jason C Del Rio <spillthetea917@gmail.com>
License: BSD 3-Clause License
Project-URL: homepage, https://github.com/Spill-Tea/BenchMatcha
Project-URL: issues, https://github.com/Spill-Tea/BenchMatcha/issues
Keywords: benchmark,regression,analysis
Classifier: Programming Language :: Python :: 3
Classifier: Development Status :: 1 - Planning
Classifier: License :: OSI Approved :: BSD License
Classifier: Intended Audience :: Developers
Classifier: Intended Audience :: Science/Research
Classifier: Topic :: Utilities
Classifier: Topic :: System :: Benchmark
Classifier: Topic :: Software Development :: Testing
Classifier: Topic :: Software Development :: Libraries
Requires-Python: >=3.11
License-File: LICENSE
Requires-Dist: google-benchmark
Requires-Dist: numpy
Requires-Dist: orjson
Requires-Dist: plotly
Requires-Dist: pytest
Requires-Dist: scipy
Requires-Dist: toml
Requires-Dist: wurlitzer
Provides-Extra: dev
Requires-Dist: BenchMatcha[commit,doc,lint,test,type]; extra == "dev"
Provides-Extra: doc
Requires-Dist: sphinx; extra == "doc"
Requires-Dist: furo; extra == "doc"
Requires-Dist: sphinx_multiversion; extra == "doc"
Provides-Extra: test
Requires-Dist: pytest; extra == "test"
Requires-Dist: coverage>=7.10.3; extra == "test"
Requires-Dist: pytest-xdist; extra == "test"
Requires-Dist: tox; extra == "test"
Provides-Extra: commit
Requires-Dist: pre-commit; extra == "commit"
Provides-Extra: lint
Requires-Dist: pylint; extra == "lint"
Requires-Dist: ruff; extra == "lint"
Provides-Extra: type
Requires-Dist: mypy; extra == "type"
Dynamic: license-file
